astrolabe/__init__.py
astrolabe/client.py
astrolabe/py.typed
astrolabe/rule_engine.py
astrolabe/settings.py
astrolabe_python_sdk-1.0.5.dist-info/licenses/LICENSE
astrolabe_python_sdk-1.0.5.dist-info/METADATA
astrolabe_python_sdk-1.0.5.dist-info/WHEEL
astrolabe_python_sdk-1.0.5.dist-info/top_level.txt
astrolabe_python_sdk-1.0.5.dist-info/RECORD
