Metadata-Version: 2.4
Name: astrolabe-python-sdk
Version: 1.0.5
Summary: Python SDK for Astrolabe feature flag system
Author-email: Astrolabe Team <md.hawamdeh@gmail.com>
License: MIT
Project-URL: Homepage, https://github.com/astrolabe/astrolabe-python-sdk
Project-URL: Documentation, https://docs.astrolabe.dev/python-sdk
Project-URL: Repository, https://github.com/astrolabe/astrolabe-python-sdk
Project-URL: Bug Tracker, https://github.com/astrolabe/astrolabe-python-sdk/issues
Keywords: feature-flags,feature-toggles,configuration,sdk
Classifier: Development Status :: 3 - Alpha
Classifier: Intended Audience :: Developers
Classifier: License :: OSI Approved :: MIT License
Classifier: Operating System :: OS Independent
Classifier: Programming Language :: Python :: 3
Classifier: Programming Language :: Python :: 3.7
Classifier: Programming Language :: Python :: 3.8
Classifier: Programming Language :: Python :: 3.9
Classifier: Programming Language :: Python :: 3.10
Classifier: Programming Language :: Python :: 3.11
Classifier: Programming Language :: Python :: 3.12
Classifier: Topic :: Software Development :: Libraries :: Python Modules
Classifier: Topic :: System :: Systems Administration
Requires-Python: >=3.7
License-File: LICENSE
Requires-Dist: requests>=2.25.0
Provides-Extra: dev
Requires-Dist: pytest>=6.0; extra == "dev"
Requires-Dist: pytest-cov>=2.0; extra == "dev"
Requires-Dist: black>=21.0; extra == "dev"
Requires-Dist: flake8>=3.8; extra == "dev"
Requires-Dist: mypy>=0.800; extra == "dev"
Dynamic: license-file
